mnt/user-data/outputs/schemalytics/schemalytics/extractors/__init__.py
mnt/user-data/outputs/schemalytics/schemalytics/generators/__init__.py
schemalytics/__init__.py
schemalytics/cli.py
schemalytics/industry_taxonomy.py
schemalytics/llm.py
schemalytics/models.py
schemalytics/planner.py
schemalytics/templates.py
schemalytics/bin/daff.py
schemalytics/extractors/__init__.py
schemalytics/extractors/postgres.py
schemalytics/generators/__init__.py
schemalytics/generators/dbt.py
schemalytics-0.1.0.dist-info/METADATA
schemalytics-0.1.0.dist-info/WHEEL
schemalytics-0.1.0.dist-info/entry_points.txt
schemalytics-0.1.0.dist-info/top_level.txt
schemalytics-0.1.0.dist-info/RECORD
