Metadata-Version: 2.4
Name: schemalytics
Version: 0.1.0
Summary: Automated dbt project generation from PostgreSQL schemas with semantic layer
License: Apache-2.0
Requires-Python: >=3.10
Requires-Dist: click>=8.0
Requires-Dist: pydantic>=2.0
Requires-Dist: sqlalchemy>=2.0
Requires-Dist: psycopg2-binary>=2.9
Requires-Dist: httpx>=0.24
Requires-Dist: jinja2>=3.0
Requires-Dist: pyyaml>=6.0
Provides-Extra: dev
Requires-Dist: pytest>=7.0; extra == "dev"
Requires-Dist: pytest-cov>=4.0; extra == "dev"
Requires-Dist: ruff>=0.1; extra == "dev"
